README.md
setup.cfg
setup.py
Torcherist.egg-info/PKG-INFO
Torcherist.egg-info/SOURCES.txt
Torcherist.egg-info/dependency_links.txt
Torcherist.egg-info/requires.txt
Torcherist.egg-info/top_level.txt
test/__init__.py
test/test_config.py
test/test_tensor.py
test/dataloader/__init__.py
test/dataloader/text/__init__.py
test/dataloader/text/test_text_dataloader.py
test/nlp/__init__.py
test/nlp/test_nlp.py
torcherist/__init__.py
torcherist/base.py
torcherist/config.py
torcherist/tensor.py
torcherist/algorithms/__init__.py
torcherist/algorithms/nlp/__init__.py
torcherist/algorithms/skill_extractors/__init__.py
torcherist/algorithms/skill_extractors/base.py
torcherist/algorithms/skill_extractors/corpus.py
torcherist/algorithms/skill_extractors/exact_match.py
torcherist/algorithms/skill_extractors/fuzzy_match.py
torcherist/algorithms/skill_extractors/noun_phrase_ending.py
torcherist/algorithms/skill_extractors/section_extract.py
torcherist/algorithms/skill_extractors/soc_exact.py
torcherist/algorithms/skill_extractors/symspell.py
torcherist/dataloader/__init__.py
torcherist/dataloader/text/__init__.py
torcherist/dataset/__init__.py
torcherist/dataset/ontology/__init__.py
torcherist/dataset/ontology/onet.py
torcherist/dataset/text/__init__.py
torcherist/dataset/text/text.py
torcherist/nlp/__init__.py
torcherist/train/__init__.py
torcherist/viz/__init__.py